[
  {
    "name": "Base",
    "passed": true,
    "size": 37369,
    "sizeLimit": 2000000,
    "loading": 0.72986328125
  },
  {
    "name": "Accordion, AccordionItemHeader, AccordionItemBody, AccordionItem",
    "passed": true,
    "size": 46182,
    "sizeLimit": 2000000,
    "loading": 0.9019921875
  },
  {
    "name": "ActionList, ActionListItem, ActionListItemAvatar, ActionListItemBadge, ActionListItemBadgeGroup, ActionListItemIcon, ActionListItemText, ActionListSection, ActionListSectionTitle",
    "passed": true,
    "size": 59089,
    "sizeLimit": 2000000,
    "loading": 1.15408203125
  },
  {
    "name": "Alert",
    "passed": true,
    "size": 49020,
    "sizeLimit": 2000000,
    "loading": 0.957421875
  },
  {
    "name": "Amount",
    "passed": true,
    "size": 38751,
    "sizeLimit": 2000000,
    "loading": 0.75685546875
  },
  {
    "name": "AnimateInteractions",
    "passed": true,
    "size": 38235,
    "sizeLimit": 2000000,
    "loading": 0.74677734375
  },
  {
    "name": "Avatar, AvatarGroup, TrustedBadgeIcon",
    "passed": true,
    "size": 43819,
    "sizeLimit": 2000000,
    "loading": 0.85583984375
  },
  {
    "name": "Badge",
    "passed": true,
    "size": 38262,
    "sizeLimit": 2000000,
    "loading": 0.7473046875
  },
  {
    "name": "useBaseMenuItem",
    "passed": true,
    "size": 37315,
    "sizeLimit": 2000000,
    "loading": 0.72880859375
  },
  {
    "name": "MotionDiv",
    "passed": true,
    "size": 37309,
    "sizeLimit": 2000000,
    "loading": 0.72869140625
  },
  {
    "name": "BladeProvider",
    "passed": true,
    "size": 39101,
    "sizeLimit": 2000000,
    "loading": 0.76369140625
  },
  {
    "name": "BottomNav, BottomNavItem",
    "passed": true,
    "size": 38491,
    "sizeLimit": 2000000,
    "loading": 0.75177734375
  },
  {
    "name": "BottomSheet",
    "passed": true,
    "size": 47045,
    "sizeLimit": 2000000,
    "loading": 0.91884765625
  },
  {
    "name": "Box",
    "passed": true,
    "size": 38235,
    "sizeLimit": 2000000,
    "loading": 0.74677734375
  },
  {
    "name": "Breadcrumb, BreadcrumbItem",
    "passed": true,
    "size": 40037,
    "sizeLimit": 2000000,
    "loading": 0.78197265625
  },
  {
    "name": "ButtonGroup",
    "passed": true,
    "size": 38702,
    "sizeLimit": 2000000,
    "loading": 0.7558984375
  },
  {
    "name": "Card, CardBody, CardHeader, CardHeaderIcon, CardHeaderIconButton, CardHeaderLeading, CardHeaderTrailing, CardFooter, CardFooterLeading, CardFooterTrailing",
    "passed": true,
    "size": 46816,
    "sizeLimit": 2000000,
    "loading": 0.914375
  },
  {
    "name": "Carousel, CarouselItem",
    "passed": true,
    "size": 44557,
    "sizeLimit": 2000000,
    "loading": 0.87025390625
  },
  {
    "name": "ChatMessage",
    "passed": true,
    "size": 40701,
    "sizeLimit": 2000000,
    "loading": 0.79494140625
  },
  {
    "name": "Checkbox",
    "passed": true,
    "size": 43773,
    "sizeLimit": 2000000,
    "loading": 0.85494140625
  },
  {
    "name": "Chip, ChipGroup",
    "passed": true,
    "size": 45943,
    "sizeLimit": 2000000,
    "loading": 0.89732421875
  },
  {
    "name": "Collapsible, CollapsibleLink, CollapsibleButton, CollapsibleBody",
    "passed": true,
    "size": 47150,
    "sizeLimit": 2000000,
    "loading": 0.9208984375
  },
  {
    "name": "Counter",
    "passed": true,
    "size": 38222,
    "sizeLimit": 2000000,
    "loading": 0.7465234375
  },
  {
    "name": "DatePicker",
    "passed": true,
    "size": 127440,
    "sizeLimit": 2000000,
    "loading": 2.4890625
  },
  {
    "name": "Divider",
    "passed": true,
    "size": 37922,
    "sizeLimit": 2000000,
    "loading": 0.7406640625
  },
  {
    "name": "Drawer, DrawerBody, DrawerHeader, drawerPadding",
    "passed": true,
    "size": 55770,
    "sizeLimit": 2000000,
    "loading": 1.0892578125
  },
  {
    "name": "Dropdown, DropdownOverlay, DropdownButton, DropdownLink, DropdownIconButton, DropdownFooter, DropdownHeader, FilterChipSelectInput, FilterChipGroup",
    "passed": true,
    "size": 70800,
    "sizeLimit": 2000000,
    "loading": 1.3828125
  },
  {
    "name": "Elevate",
    "passed": true,
    "size": 38253,
    "sizeLimit": 2000000,
    "loading": 0.74712890625
  },
  {
    "name": "Fade",
    "passed": true,
    "size": 38418,
    "sizeLimit": 2000000,
    "loading": 0.7503515625
  },
  {
    "name": "FileUpload",
    "passed": true,
    "size": 55521,
    "sizeLimit": 2000000,
    "loading": 1.08439453125
  },
  {
    "name": "Indicator",
    "passed": true,
    "size": 38460,
    "sizeLimit": 2000000,
    "loading": 0.751171875
  },
  {
    "name": "List, ListItem, ListItemLink, ListItemCode, ListItemText",
    "passed": true,
    "size": 42615,
    "sizeLimit": 2000000,
    "loading": 0.83232421875
  },
  {
    "name": "ListView, ListViewFilters",
    "passed": true,
    "size": 78961,
    "sizeLimit": 2000000,
    "loading": 1.54220703125
  },
  {
    "name": "Menu, MenuItem, MenuOverlay, MenuDivider, MenuFooter, MenuHeader",
    "passed": true,
    "size": 67489,
    "sizeLimit": 2000000,
    "loading": 1.31814453125
  },
  {
    "name": "Modal",
    "passed": true,
    "size": 50799,
    "sizeLimit": 2000000,
    "loading": 0.99216796875
  },
  {
    "name": "Morph",
    "passed": true,
    "size": 37613,
    "sizeLimit": 2000000,
    "loading": 0.73462890625
  },
  {
    "name": "Move",
    "passed": true,
    "size": 38449,
    "sizeLimit": 2000000,
    "loading": 0.75095703125
  },
  {
    "name": "Popover, PopoverInteractiveWrapper",
    "passed": true,
    "size": 58939,
    "sizeLimit": 2000000,
    "loading": 1.15115234375
  },
  {
    "name": "Preview, PreviewBody, PreviewFooter, PreviewHeader",
    "passed": true,
    "size": 51850,
    "sizeLimit": 2000000,
    "loading": 1.0126953125
  },
  {
    "name": "ProgressBar",
    "passed": true,
    "size": 40428,
    "sizeLimit": 2000000,
    "loading": 0.789609375
  },
  {
    "name": "QuickFilter, QuickFilterGroup",
    "passed": true,
    "size": 50574,
    "sizeLimit": 2000000,
    "loading": 0.9877734375
  },
  {
    "name": "Radio",
    "passed": true,
    "size": 42476,
    "sizeLimit": 2000000,
    "loading": 0.829609375
  },
  {
    "name": "Scale",
    "passed": true,
    "size": 38263,
    "sizeLimit": 2000000,
    "loading": 0.74732421875
  },
  {
    "name": "SideNav, SideNavLink, SideNavLevel, SideNavSection, SideNavItem, SideNavFooter, SideNavBody, SIDE_NAV_EXPANDED_L1_WIDTH_BASE, SIDE_NAV_EXPANDED_L1_WIDTH_XL",
    "passed": true,
    "size": 71931,
    "sizeLimit": 2000000,
    "loading": 1.40490234375
  },
  {
    "name": "Skeleton",
    "passed": true,
    "size": 38138,
    "sizeLimit": 2000000,
    "loading": 0.7448828125
  },
  {
    "name": "Slide",
    "passed": true,
    "size": 38631,
    "sizeLimit": 2000000,
    "loading": 0.75451171875
  },
  {
    "name": "SpotlightPopoverTour, SpotlightPopoverTourFooter, SpotlightPopoverTourStep",
    "passed": true,
    "size": 67304,
    "sizeLimit": 2000000,
    "loading": 1.31453125
  },
  {
    "name": "Stagger",
    "passed": true,
    "size": 38291,
    "sizeLimit": 2000000,
    "loading": 0.74787109375
  },
  {
    "name": "StepGroup, StepItem, StepItemIcon, StepItemIndicator",
    "passed": true,
    "size": 44177,
    "sizeLimit": 2000000,
    "loading": 0.86283203125
  },
  {
    "name": "Switch",
    "passed": true,
    "size": 42251,
    "sizeLimit": 2000000,
    "loading": 0.82521484375
  },
  {
    "name": "Table, TableHeader, TableHeaderCell, TableHeaderRow, TableBody, TableCell, TableRow, TableFooter, TableFooterCell, TableFooterRow, TablePagination, TableToolbar, TableToolbarActions, TableEditableCell, TableEditableDropdownCell",
    "passed": true,
    "size": 110618,
    "sizeLimit": 2000000,
    "loading": 2.1605078125
  },
  {
    "name": "Tabs, TabItem, TabList, TabPanel",
    "passed": true,
    "size": 44470,
    "sizeLimit": 2000000,
    "loading": 0.8685546875
  },
  {
    "name": "Tag",
    "passed": true,
    "size": 41342,
    "sizeLimit": 2000000,
    "loading": 0.8074609375
  },
  {
    "name": "ToastContainer, useToast",
    "passed": true,
    "size": 50480,
    "sizeLimit": 2000000,
    "loading": 0.9859375
  },
  {
    "name": "Tooltip, TooltipInteractiveWrapper",
    "passed": true,
    "size": 53493,
    "sizeLimit": 2000000,
    "loading": 1.04478515625
  },
  {
    "name": "TopNav, TopNavActions, TopNavBrand, TopNavContent",
    "passed": true,
    "size": 38009,
    "sizeLimit": 2000000,
    "loading": 0.74236328125
  },
  {
    "name": "Button",
    "passed": true,
    "size": 43537,
    "sizeLimit": 2000000,
    "loading": 0.85033203125
  },
  {
    "name": "IconButton",
    "passed": true,
    "size": 38545,
    "sizeLimit": 2000000,
    "loading": 0.75283203125
  },
  {
    "name": "CheckboxGroup",
    "passed": true,
    "size": 42525,
    "sizeLimit": 2000000,
    "loading": 0.83056640625
  },
  {
    "name": "FilterChipDatePicker",
    "passed": true,
    "size": 127433,
    "sizeLimit": 2000000,
    "loading": 2.48892578125
  },
  {
    "name": "SelectInput, AutoComplete",
    "passed": true,
    "size": 74198,
    "sizeLimit": 2000000,
    "loading": 1.4491796875
  },
  {
    "name": "OTPInput",
    "passed": true,
    "size": 67794,
    "sizeLimit": 2000000,
    "loading": 1.3241015625
  },
  {
    "name": "PasswordInput",
    "passed": true,
    "size": 69598,
    "sizeLimit": 2000000,
    "loading": 1.3593359375
  },
  {
    "name": "PhoneNumberInput",
    "passed": true,
    "size": 103315,
    "sizeLimit": 2000000,
    "loading": 2.01787109375
  },
  {
    "name": "SearchInput",
    "passed": true,
    "size": 72330,
    "sizeLimit": 2000000,
    "loading": 1.4126953125
  },
  {
    "name": "TextArea",
    "passed": true,
    "size": 70126,
    "sizeLimit": 2000000,
    "loading": 1.3696484375
  },
  {
    "name": "TextInput",
    "passed": true,
    "size": 71648,
    "sizeLimit": 2000000,
    "loading": 1.399375
  },
  {
    "name": "Link",
    "passed": true,
    "size": 39577,
    "sizeLimit": 2000000,
    "loading": 0.77298828125
  },
  {
    "name": "QuickFilterGroup, QuickFilterGroupProvider, useQuickFilterGroupContext",
    "passed": true,
    "size": 43252,
    "sizeLimit": 2000000,
    "loading": 0.844765625
  },
  {
    "name": "RadioGroup",
    "passed": true,
    "size": 42534,
    "sizeLimit": 2000000,
    "loading": 0.8307421875
  },
  {
    "name": "Spinner",
    "passed": true,
    "size": 39279,
    "sizeLimit": 2000000,
    "loading": 0.76716796875
  },
  {
    "name": "getTableBodyStyles",
    "passed": true,
    "size": 37313,
    "sizeLimit": 2000000,
    "loading": 0.72876953125
  },
  {
    "name": "TabNav, TabNavItems, TabNavItem",
    "passed": true,
    "size": 39802,
    "sizeLimit": 2000000,
    "loading": 0.7773828125
  },
  {
    "name": "Code",
    "passed": true,
    "size": 37984,
    "sizeLimit": 2000000,
    "loading": 0.741875
  },
  {
    "name": "Display",
    "passed": true,
    "size": 37695,
    "sizeLimit": 2000000,
    "loading": 0.73623046875
  },
  {
    "name": "Heading, getHeadingProps",
    "passed": true,
    "size": 37693,
    "sizeLimit": 2000000,
    "loading": 0.73619140625
  },
  {
    "name": "Text",
    "passed": true,
    "size": 37371,
    "sizeLimit": 2000000,
    "loading": 0.72990234375
  }
]
